{
  "data": [
    {
      "id": "1",
      "name": "白水晶1",
      "image_url": "https://zhuluoji.cn-sh2.ufileos.com/beads/%E7%99%BD%E6%B0%B4%E6%99%B61.png",
      "color": "白色",
      "wuxing": "金",
      "english": "White Quartz 1"
    },
    {
      "id": "2",
      "name": "白水晶2",
      "image_url": "https://zhuluoji.cn-sh2.ufileos.com/beads/%E7%99%BD%E6%B0%B4%E6%99%B62.png",
      "color": "白色",
      "wuxing": "金",
      "english": "White Quartz 2"
    },
    {
      "id": "3",
      "name": "白松石",
      "image_url": "https://zhuluoji.cn-sh2.ufileos.com/beads/%E7%99%BD%E6%9D%BE%E7%9F%B3.png",
      "color": "白色",
      "wuxing": "金",
      "english": "White Turquoise"
    },
    {
      "id": "4",
      "name": "冰飘南红",
      "image_url": "https://zhuluoji.cn-sh2.ufileos.com/beads/%E5%86%B0%E9%A3%98%E5%8D%97%E7%BA%A2.png",
      "color": "橙色、红色",
      "wuxing": "火",
      "english": "Ice-Flotting South Red Agate"
    },
    {
      "id": "5",
      "name": "玻璃球",
      "image_url": "https://zhuluoji.cn-sh2.ufileos.com/beads/%E7%8E%BB%E7%92%83%E7%90%83.png",
      "color": "白色、蓝色",
      "wuxing": "金、火、土",
      "english": "Glass Ball"
    },
    {
      "id": "6",
      "name": "玻璃球2",
      "image_url": "https://zhuluoji.cn-sh2.ufileos.com/beads/%E7%8E%BB%E7%92%83%E7%90%832.png",
      "color": "白色",
      "wuxing": "金、木、土",
      "english": "Glass Ball 2"
    },
    {
      "id": "7",
      "name": "玻璃球3",
      "image_url": "https://zhuluoji.cn-sh2.ufileos.com/beads/%E7%8E%BB%E7%92%83%E7%90%833.png",
      "color": "白色、紫色、黄色、蓝色、粉色、绿色",
      "wuxing": "金、木、水、火、土",
      "english": "Glass Ball 3"
    },
    {
      "id": "8",
      "name": "玻璃球5",
      "image_url": "https://zhuluoji.cn-sh2.ufileos.com/beads/%E7%8E%BB%E7%92%83%E7%90%835.png",
      "color": "粉色",
      "wuxing": "金",
      "english": "Glass Ball 5"
    },
    {
      "id": "9",
      "name": "玻璃球6",
      "image_url": "https://zhuluoji.cn-sh2.ufileos.com/beads/%E7%8E%BB%E7%92%83%E7%90%836.png",
      "color": "蓝色",
      "wuxing": "金、木、水、火、土",
      "english": "Glass Ball 6"
    },
    {
      "id": "10",
      "name": "玻璃球7",
      "image_url": "https://zhuluoji.cn-sh2.ufileos.com/beads/%E7%8E%BB%E7%92%83%E7%90%837.png",
      "color": "浅蓝色",
      "wuxing": "土",
      "english": "Glass Ball 7"
    },
    {
      "id": "11",
      "name": "草莓晶1",
      "image_url": "https://zhuluoji.cn-sh2.ufileos.com/beads/%E8%8D%89%E8%8E%93%E6%99%B61.png",
      "color": "红色",
      "wuxing": "火、金、土",
      "english": "Strawberry Quartz 1"
    },
    {
      "id": "12",
      "name": "草莓水晶",
      "image_url": "https://zhuluoji.cn-sh2.ufileos.com/beads/%E8%8D%89%E8%8E%93%E6%B0%B4%E6%99%B6.png",
      "color": "红色",
      "wuxing": "火、木",
      "english": "Strawberry Quartz"
    },
    {
      "id": "13",
      "name": "蛋白石",
      "image_url": "https://zhuluoji.cn-sh2.ufileos.com/beads/%E8%9B%8B%E7%99%BD%E7%9F%B3.png",
      "color": "浅绿色",
      "wuxing": "金、水",
      "english": "Opal"
    },
    {
      "id": "14",
      "name": "粉水晶",
      "image_url": "https://zhuluoji.cn-sh2.ufileos.com/beads/%E7%B2%89%E6%B0%B4%E6%99%B6.png",
      "color": "粉色",
      "wuxing": "火、土、水、金",
      "english": "Rose Quartz"
    },
    {
      "id": "15",
      "name": "粉水晶1",
      "image_url": "https://zhuluoji.cn-sh2.ufileos.com/beads/%E7%B2%89%E6%B0%B4%E6%99%B61.png",
      "color": "粉红色",
      "wuxing": "火",
      "english": "Rose Quartz 1"
    },
    {
      "id": "16",
      "name": "粉水晶4",
      "image_url": "https://zhuluoji.cn-sh2.ufileos.com/beads/%E7%B2%89%E6%B0%B4%E6%99%B64.png",
      "color": "粉色",
      "wuxing": "火",
      "english": "Rose Quartz 4"
    },
    {
      "id": "17",
      "name": "粉水晶5",
      "image_url": "https://zhuluoji.cn-sh2.ufileos.com/beads/%E7%B2%89%E6%B0%B4%E6%99%B65.png",
      "color": "红色",
      "wuxing": "火、土、水",
      "english": "Rose Quartz 5"
    },
    {
      "id": "18",
      "name": "粉水晶6",
      "image_url": "https://zhuluoji.cn-sh2.ufileos.com/beads/%E7%B2%89%E6%B0%B4%E6%99%B66.png",
      "color": "粉色",
      "wuxing": "火、土",
      "english": "Rose Quartz 6"
    },
    {
      "id": "19",
      "name": "海蓝宝",
      "image_url": "https://zhuluoji.cn-sh2.ufileos.com/beads/%E6%B5%B7%E8%93%9D%E5%AE%9D.png",
      "color": "蓝色",
      "wuxing": "水",
      "english": "Aquamarine"
    },
    {
      "id": "20",
      "name": "海蓝宝1",
      "image_url": "https://zhuluoji.cn-sh2.ufileos.com/beads/%E6%B5%B7%E8%93%9D%E5%AE%9D1.png",
      "color": "蓝色",
      "wuxing": "水、金",
      "english": "Aquamarine 1"
    },
    {
      "id": "21",
      "name": "海螺珠",
      "image_url": "https://zhuluoji.cn-sh2.ufileos.com/beads/%E6%B5%B7%E8%9E%BA%E7%8F%A0.png",
      "color": "橙色",
      "wuxing": "金",
      "english": "Seashell Pearl"
    },
    {
      "id": "22",
      "name": "和田玉",
      "image_url": "https://zhuluoji.cn-sh2.ufileos.com/beads/%E5%92%8C%E7%94%B0%E7%8E%89.png",
      "color": "浅绿色",
      "wuxing": "土",
      "english": "Hetian Jade"
    },
    {
      "id": "23",
      "name": "黑玛瑙",
      "image_url": "https://zhuluoji.cn-sh2.ufileos.com/beads/%E9%BB%91%E7%8E%9B%E7%91%99.png",
      "color": "黑色",
      "wuxing": "水",
      "english": "Black Agate"
    },
    {
      "id": "24",
      "name": "黑曜石",
      "image_url": "https://zhuluoji.cn-sh2.ufileos.com/beads/%E9%BB%91%E6%9B%9C%E7%9F%B3.png",
      "color": "黑色",
      "wuxing": "火",
      "english": "Obsidian"
    },
    {
      "id": "25",
      "name": "红碧石",
      "image_url": "https://zhuluoji.cn-sh2.ufileos.com/beads/%E7%BA%A2%E7%A2%A7%E7%9F%B3.png",
      "color": "红色",
      "wuxing": "火",
      "english": "Red Jasper"
    },
    {
      "id": "26",
      "name": "红胶花",
      "image_url": "https://zhuluoji.cn-sh2.ufileos.com/beads/%E7%BA%A2%E8%83%B6%E8%8A%B1.png",
      "color": "红色",
      "wuxing": "火",
      "english": "Red Flower Agate"
    },
    {
      "id": "27",
      "name": "红胶花 2",
      "image_url": "https://zhuluoji.cn-sh2.ufileos.com/beads/%E7%BA%A2%E8%83%B6%E8%8A%B12.png",
      "color": "橙色、白色",
      "wuxing": "火",
      "english": "Red Flower Agate 2"
    },
    {
      "id": "28",
      "name": "红胶花 3",
      "image_url": "https://zhuluoji.cn-sh2.ufileos.com/beads/%E7%BA%A2%E8%83%B6%E8%8A%B13.png",
      "color": "棕色、黑色",
      "wuxing": "火",
      "english": "Red Flower Agate 3"
    },
    {
      "id": "29",
      "name": "红水晶",
      "image_url": "https://zhuluoji.cn-sh2.ufileos.com/beads/%E7%BA%A2%E6%B0%B4%E6%99%B6.png",
      "color": "红色",
      "wuxing": "火、金、土",
      "english": "Red Quartz"
    },
    {
      "id": "30",
      "name": "红水晶 3",
      "image_url": "https://zhuluoji.cn-sh2.ufileos.com/beads/%E7%BA%A2%E6%B0%B4%E6%99%B63.png",
      "color": "红色",
      "wuxing": "火",
      "english": "Red Quartz 3"
    },
    {
      "id": "31",
      "name": "虎眼石 - 蓝色",
      "image_url": "https://zhuluoji.cn-sh2.ufileos.com/beads/%E8%99%8E%E7%9C%BC%E7%9F%B3-%E8%93%9D%E8%89%B2.png",
      "color": "黑色",
      "wuxing": "水",
      "english": "Blue Tiger's Eye"
    },
    {
      "id": "32",
      "name": "虎眼石 - 蓝色 2",
      "image_url": "https://zhuluoji.cn-sh2.ufileos.com/beads/%E8%99%8E%E7%9C%BC%E7%9F%B3-%E8%93%9D%E8%89%B22.png",
      "color": "蓝色",
      "wuxing": "金、土",
      "english": "Blue Tiger's Eye 2"
    },
    {
      "id": "33",
      "name": "虎眼石",
      "image_url": "https://zhuluoji.cn-sh2.ufileos.com/beads/%E8%99%8E%E7%9C%BC%E7%9F%B3.png",
      "color": "棕色、黄色",
      "wuxing": "金、木、土",
      "english": "Tiger's Eye"
    },
    {
      "id": "34",
      "name": "黄发晶 2",
      "image_url": "https://zhuluoji.cn-sh2.ufileos.com/beads/%E8%99%8E%E7%9C%BC%E7%9F%B32.png",
      "color": "棕色",
      "wuxing": "土",
      "english": "Yellow Rutilated Quartz 2"
    },
    {
      "id": "35",
      "name": "黄玛瑙",
      "image_url": "https://zhuluoji.cn-sh2.ufileos.com/beads/%E9%BB%84%E5%8F%91%E6%99%B6.png",
      "color": "金黄色",
      "wuxing": "土",
      "english": "Yellow Agate"
    },
    {
      "id": "36",
      "name": "黄色萤石",
      "image_url": "https://zhuluoji.cn-sh2.ufileos.com/beads/%E9%BB%84%E7%8E%9B%E7%91%99.png",
      "color": "黄色",
      "wuxing": "土",
      "english": "Yellow Fluorite"
    },
    {
      "id": "37",
      "name": "黄色宝石",
      "image_url": "https://zhuluoji.cn-sh2.ufileos.com/beads/%E9%BB%84%E8%89%B2%E8%9A%82%E7%9F%B3.png",
      "color": "黄色",
      "wuxing": "土、金",
      "english": "Yellow Gemstone"
    },
    {
      "id": "38",
      "name": "黄水晶",
      "image_url": "https://zhuluoji.cn-sh2.ufileos.com/beads/%E9%BB%84%E6%B0%B4%E6%99%B6.png",
      "color": "浅黄色",
      "wuxing": "土",
      "english": "Citrine"
    },
    {
      "id": "39",
      "name": "黄水晶 1",
      "image_url": "https://zhuluoji.cn-sh2.ufileos.com/beads/%E9%BB%84%E6%B0%B4%E6%99%B61.png",
      "color": "黄色",
      "wuxing": "土",
      "english": "Citrine 1"
    },
    {
      "id": "40",
      "name": "黄水晶 2",
      "image_url": "https://zhuluoji.cn-sh2.ufileos.com/beads/%E9%BB%84%E6%B0%B4%E6%99%B62.png",
      "color": "棕色",
      "wuxing": "土",
      "english": "Citrine 2"
    },
    {
      "id": "41",
      "name": "黄水晶 3",
      "image_url": "https://zhuluoji.cn-sh2.ufileos.com/beads/%E9%BB%84%E6%B0%B4%E6%99%B63.png",
      "color": "金色、白色、绿色",
      "wuxing": "土",
      "english": "Citrine 3"
    },
    {
      "id": "42",
      "name": "黄水晶 4",
      "image_url": "https://zhuluoji.cn-sh2.ufileos.com/beads/%E9%BB%84%E6%B0%B4%E6%99%B64.png",
      "color": "黄色",
      "wuxing": "土、金、火",
      "english": "Citrine 4"
    },
    {
      "id": "43",
      "name": "火焰石",
      "image_url": "https://zhuluoji.cn-sh2.ufileos.com/beads/%E7%81%AB%E7%84%B0%E7%9F%B3.png",
      "color": "灰色、黑色、棕色、紫色",
      "wuxing": "火",
      "english": "Flame Stone"
    },
    {
      "id": "44",
      "name": "金冻石",
      "image_url": "https://zhuluoji.cn-sh2.ufileos.com/beads/%E9%87%91%E5%86%BB%E7%9F%B3.png",
      "color": "橙色",
      "wuxing": "火",
      "english": "Golden Jelly Stone"
    },
    {
      "id": "45",
      "name": "金绿猫眼",
      "image_url": "https://zhuluoji.cn-sh2.ufileos.com/beads/%E9%87%91%E7%BB%BF%E7%8C%AB%E7%9C%BC.png",
      "color": "黄色",
      "wuxing": "土",
      "english": "Chrysoberyl Cat's Eye"
    },
    {
      "id": "46",
      "name": "金丝玉",
      "image_url": "https://zhuluoji.cn-sh2.ufileos.com/beads/%E9%87%91%E4%B8%9D%E7%8E%89.png",
      "color": "棕色、黄色",
      "wuxing": "金",
      "english": "Jinsi Jade"
    },
    {
      "id": "47",
      "name": "金耀石",
      "image_url": "https://zhuluoji.cn-sh2.ufileos.com/beads/%E9%87%91%E8%80%80%E7%9F%B3.png",
      "color": "黑色、金色",
      "wuxing": "金、土",
      "english": "Gold Sheen Obsidian"
    },
    {
      "id": "48",
      "name": "金珠",
      "image_url": "https://zhuluoji.cn-sh2.ufileos.com/beads/%E9%87%91%E7%8F%A0.png",
      "color": "黄色",
      "wuxing": "金",
      "english": "Gold Bead"
    },
    {
      "id": "49",
      "name": "金珠 2",
      "image_url": "https://zhuluoji.cn-sh2.ufileos.com/beads/%E9%87%91%E7%8F%A02.png",
      "color": "金色",
      "wuxing": "土",
      "english": "Gold Bead 2"
    },
    {
      "id": "50",
      "name": "拉长石",
      "image_url": "https://zhuluoji.cn-sh2.ufileos.com/beads/%E6%8B%89%E9%95%BF%E7%9F%B3.png",
      "color": "蓝色、绿色、棕色",
      "wuxing": "水",
      "english": "Labradorite"
    },
    {
      "id": "51",
      "name": "拉长石 1",
      "image_url": "https://zhuluoji.cn-sh2.ufileos.com/beads/%E6%8B%89%E9%95%BF%E7%9F%B31.png",
      "color": "蓝色",
      "wuxing": "水",
      "english": "Labradorite 1"
    },
    {
      "id": "52",
      "name": "蓝力士",
      "image_url": "https://zhuluoji.cn-sh2.ufileos.com/beads/%E8%93%9D%E5%8A%9B%E5%A3%AB.png",
      "color": "蓝色、棕色、灰色、白色",
      "wuxing": "水、木",
      "english": "Blue Spinel"
    },
    {
      "id": "53",
      "name": "蓝纹玛瑙",
      "image_url": "https://zhuluoji.cn-sh2.ufileos.com/beads/%E8%93%9D%E7%BA%B9%E7%8E%9B%E7%91%99.png",
      "color": "浅蓝色",
      "wuxing": "水",
      "english": "Blue Lace Agate"
    },
    {
      "id": "54",
      "name": "蓝纹石",
      "image_url": "https://zhuluoji.cn-sh2.ufileos.com/beads/%E8%93%9D%E7%BA%B9%E7%9F%B3.png",
      "color": "蓝色",
      "wuxing": "水",
      "english": "Blue Vein Stone"
    },
    {
      "id": "55",
      "name": "蓝玉髓",
      "image_url": "https://zhuluoji.cn-sh2.ufileos.com/beads/%E8%93%9D%E7%8E%89%E9%AB%93.png",
      "color": "浅蓝色",
      "wuxing": "水",
      "english": "Blue Chalcedony"
    },
    {
      "id": "56",
      "name": "磷灰石 - 蓝色",
      "image_url": "https://zhuluoji.cn-sh2.ufileos.com/beads/%E7%A3%B7%E7%81%B0%E7%9F%B3-%E8%93%9D%E8%89%B2.png",
      "color": "蓝色",
      "wuxing": "水",
      "english": "Blue Apatite"
    },
    {
      "id": "57",
      "name": "磷灰石 - 蓝色 1",
      "image_url": "https://zhuluoji.cn-sh2.ufileos.com/beads/%E7%A3%B7%E7%81%B0%E7%9F%B3-%E8%93%9D%E8%89%B21.png",
      "color": "蓝色",
      "wuxing": "水",
      "english": "Blue Apatite 1"
    },
    {
      "id": "58",
      "name": "磷灰石 - 蓝色 2",
      "image_url": "https://zhuluoji.cn-sh2.ufileos.com/beads/%E7%A3%B7%E7%81%B0%E7%9F%B3-%E8%93%9D%E8%89%B22.png",
      "color": "蓝色",
      "wuxing": "水",
      "english": "Blue Apatite 2"
    },
    {
      "id": "59",
      "name": "绿东陵",
      "image_url": "https://zhuluoji.cn-sh2.ufileos.com/beads/%E7%BB%BF%E4%B8%9C%E9%99%B5.png",
      "color": "绿色",
      "wuxing": "木",
      "english": "Green Aventurine"
    },
    {
      "id": "60",
      "name": "绿翡翠",
      "image_url": "https://zhuluoji.cn-sh2.ufileos.com/beads/%E7%BB%BF%E7%BF%A1%E7%BF%A0.png",
      "color": "绿色",
      "wuxing": "木",
      "english": "Green Jadeite"
    },
    {
      "id": "61",
      "name": "绿玛瑙",
      "image_url": "https://zhuluoji.cn-sh2.ufileos.com/beads/%E7%BB%BF%E7%8E%9B%E7%91%99.png",
      "color": "绿色",
      "wuxing": "木",
      "english": "Green Agate"
    },
    {
      "id": "62",
      "name": "绿玛瑙 2",
      "image_url": "https://zhuluoji.cn-sh2.ufileos.com/beads/%E7%BB%BF%E7%8E%9B%E7%91%992.png",
      "color": "绿色",
      "wuxing": "木",
      "english": "Green Agate 2"
    },
    {
      "id": "63",
      "name": "绿葡萄石",
      "image_url": "https://zhuluoji.cn-sh2.ufileos.com/beads/%E7%BB%BF%E8%91%A1%E8%90%84%E7%9F%B3.png",
      "color": "绿色",
      "wuxing": "木",
      "english": "Green Prehnite"
    },
    {
      "id": "64",
      "name": "绿松石",
      "image_url": "https://zhuluoji.cn-sh2.ufileos.com/beads/%E7%BB%BF%E6%9D%BE%E7%9F%B3.png",
      "color": "青绿色",
      "wuxing": "水、木、土",
      "english": "Turquoise"
    },
    {
      "id": "65",
      "name": "绿松石 2",
      "image_url": "https://zhuluoji.cn-sh2.ufileos.com/beads/%E7%BB%BF%E6%9D%BE%E7%9F%B32.png",
      "color": "青绿色",
      "wuxing": "木、水、土",
      "english": "Turquoise 2"
    },
    {
      "id": "66",
      "name": "绿松石 3",
      "image_url": "https://zhuluoji.cn-sh2.ufileos.com/beads/%E7%BB%BF%E6%9D%BE%E7%9F%B33.png",
      "color": "绿色",
      "wuxing": "木",
      "english": "Turquoise 3"
    },
    {
      "id": "67",
      "name": "绿萤石",
      "image_url": "https://zhuluoji.cn-sh2.ufileos.com/beads/%E7%BB%BF%E8%9A%82%E7%9F%B3.png",
      "color": "绿色",
      "wuxing": "木",
      "english": "Green Fluorite"
    },
    {
      "id": "68",
      "name": "绿萤石 2",
      "image_url": "https://zhuluoji.cn-sh2.ufileos.com/beads/%E7%BB%BF%E8%9A%82%E7%9F%B32.png",
      "color": "浅绿色",
      "wuxing": "木",
      "english": "Green Fluorite 2"
    },
    {
      "id": "69",
      "name": "玛瑙",
      "image_url": "https://zhuluoji.cn-sh2.ufileos.com/beads/%E7%8E%9B%E7%91%99.png",
      "color": "棕色、浅棕色、深棕色",
      "wuxing": "木",
      "english": "Agate"
    },
    {
      "id": "70",
      "name": "玛瑙 1",
      "image_url": "https://zhuluoji.cn-sh2.ufileos.com/beads/%E7%8E%9B%E7%91%991.png",
      "color": "红色、橙色、浅棕色",
      "wuxing": "火",
      "english": "Agate 1"
    },
    {
      "id": "71",
      "name": "玛瑙 2",
      "image_url": "https://zhuluoji.cn-sh2.ufileos.com/beads/%E7%8E%9B%E7%91%992.png",
      "color": "橙色、黄色",
      "wuxing": "火",
      "english": "Agate 2"
    },
    {
      "id": "72",
      "name": "玛瑙 3",
      "image_url": "https://zhuluoji.cn-sh2.ufileos.com/beads/%E7%8E%9B%E7%91%993.png",
      "color": "橙色",
      "wuxing": "火",
      "english": "Agate 3"
    },
    {
      "id": "73",
      "name": "蜜蜡",
      "image_url": "https://zhuluoji.cn-sh2.ufileos.com/beads/%E8%9C%9C%E8%9C%A1.png",
      "color": "黄色",
      "wuxing": "土",
      "english": "Amber"
    },
    {
      "id": "74",
      "name": "木化石",
      "image_url": "https://zhuluoji.cn-sh2.ufileos.com/beads/%E6%9C%A8%E5%8C%96%E7%9F%B3.png",
      "color": "棕色、白色",
      "wuxing": "金、木、土",
      "english": "Petrified Wood"
    },
    {
      "id": "75",
      "name": "蔷薇石",
      "image_url": "https://zhuluoji.cn-sh2.ufileos.com/beads/%E8%94%B7%E8%96%87%E7%9F%B3.png",
      "color": "粉红色",
      "wuxing": "火",
      "english": "Rhodonite"
    },
    {
      "id": "76",
      "name": "羟磷铝石",
      "image_url": "https://zhuluoji.cn-sh2.ufileos.com/beads/%E7%BE%9F%E7%A3%B7%E9%93%9D%E7%90%83.png",
      "color": "蓝色、黄色、灰色",
      "wuxing": "水",
      "english": "Variscite"
    },
    {
      "id": "77",
      "name": "青金石",
      "image_url": "https://zhuluoji.cn-sh2.ufileos.com/beads/%E9%9D%92%E9%87%91%E7%9F%B3.png",
      "color": "蓝色、金色、白色",
      "wuxing": "水、金、土",
      "english": "Lapis Lazuli"
    },
    {
      "id": "78",
      "name": "青金石 2",
      "image_url": "https://zhuluoji.cn-sh2.ufileos.com/beads/%E9%9D%92%E9%87%91%E7%9F%B32.png",
      "color": "蓝色",
      "wuxing": "水",
      "english": "Lapis Lazuli 2"
    },
    {
      "id": "79",
      "name": "石榴石",
      "image_url": "https://zhuluoji.cn-sh2.ufileos.com/beads/%E7%9F%B3%E6%A6%B4%E7%9F%B3.png",
      "color": "红色",
      "wuxing": "火",
      "english": "Garnet"
    },
    {
      "id": "80",
      "name": "水草玛瑙",
      "image_url": "https://zhuluoji.cn-sh2.ufileos.com/beads/%E6%B0%B4%E8%8D%89%E7%8E%9B%E7%91%99.png",
      "color": "绿色、白色",
      "wuxing": "木",
      "english": "Moss Agate"
    },
    {
      "id": "81",
      "name": "水草玛瑙 2",
      "image_url": "https://zhuluoji.cn-sh2.ufileos.com/beads/%E6%B0%B4%E8%8D%89%E7%8E%9B%E7%91%992.png",
      "color": "绿色",
      "wuxing": "水、木",
      "english": "Moss Agate 2"
    },
    {
      "id": "82",
      "name": "水草玛瑙 3",
      "image_url": "https://zhuluoji.cn-sh2.ufileos.com/beads/%E6%B0%B4%E8%8D%89%E7%8E%9B%E7%91%993.png",
      "color": "白色、黑色、绿色",
      "wuxing": "木、水",
      "english": "Moss Agate 3"
    },
    {
      "id": "83",
      "name": "太阳石",
      "image_url": "https://zhuluoji.cn-sh2.ufileos.com/beads/%E5%A4%AA%E9%98%B3%E7%9F%B3.png",
      "color": "浅橙色",
      "wuxing": "金、火",
      "english": "Sunstone"
    },
    {
      "id": "84",
      "name": "太阳石 1",
      "image_url": "https://zhuluoji.cn-sh2.ufileos.com/beads/%E5%A4%AA%E9%98%B3%E7%9F%B31.png",
      "color": "红色",
      "wuxing": "金、火",
      "english": "Sunstone 1"
    },
    {
      "id": "85",
      "name": "天河石",
      "image_url": "https://zhuluoji.cn-sh2.ufileos.com/beads/%E5%A4%A9%E6%B2%B3%E7%9F%B3.png",
      "color": "深蓝色、浅蓝色、灰色",
      "wuxing": "水、木、水木",
      "english": "Amazonite"
    },
    {
      "id": "86",
      "name": "雪花黑曜石",
      "image_url": "https://zhuluoji.cn-sh2.ufileos.com/beads/%E9%9B%AA%E8%8A%B1%E9%BB%91%E6%9B%9C%E7%9F%B3.png",
      "color": "黑色、白色",
      "wuxing": "水",
      "english": "Snowflake Obsidian"
    },
    {
      "id": "87",
      "name": "雪花黑曜石 1",
      "image_url": "https://zhuluoji.cn-sh2.ufileos.com/beads/%E9%9B%AA%E8%8A%B1%E9%BB%91%E6%9B%9C%E7%9F%B31.png",
      "color": "黑色、白色",
      "wuxing": "火",
      "english": "Snowflake Obsidian 1"
    },
    {
      "id": "88",
      "name": "血滴堇青石",
      "image_url": "https://zhuluoji.cn-sh2.ufileos.com/beads/%E8%A1%80%E6%BB%B4%E5%A0%87%E9%9D%92%E7%9F%B3.png",
      "color": "棕色、灰色、白色",
      "wuxing": "水",
      "english": "Blood Drop Iolite"
    },
    {
      "id": "89",
      "name": "樱花玛瑙",
      "image_url": "https://zhuluoji.cn-sh2.ufileos.com/beads/%E6%A8%B1%E8%8A%B1%E7%8E%9B%E7%91%99.png",
      "color": "橙色、白色、黑色",
      "wuxing": "木",
      "english": "Cherry Blossom Agate"
    },
    {
      "id": "90",
      "name": "樱花玛瑙 1",
      "image_url": "https://zhuluoji.cn-sh2.ufileos.com/beads/%E6%A8%B1%E8%8A%B1%E7%8E%9B%E7%91%991.png",
      "color": "粉色、紫色",
      "wuxing": "木",
      "english": "Cherry Blossom Agate 1"
    },
    {
      "id": "91",
      "name": "樱花玛瑙 2",
      "image_url": "https://zhuluoji.cn-sh2.ufileos.com/beads/%E6%A8%B1%E8%8A%B1%E7%8E%9B%E7%91%992.png",
      "color": "棕色、灰色",
      "wuxing": "金、木、水、火、土",
      "english": "Cherry Blossom Agate 2"
    },
    {
      "id": "92",
      "name": "月光石",
      "image_url": "https://zhuluoji.cn-sh2.ufileos.com/beads/%E6%9C%88%E5%85%89%E7%9F%B3.png",
      "color": "蓝色、白色",
      "wuxing": "金、木、水、火、土",
      "english": "Moonstone"
    },
    {
      "id": "93",
      "name": "月光石 2",
      "image_url": "https://zhuluoji.cn-sh2.ufileos.com/beads/%E6%9C%88%E5%85%89%E7%9F%B32.png",
      "color": "蓝色",
      "wuxing": "水、木、土、金",
      "english": "Moonstone 2"
    },
    {
      "id": "94",
      "name": "珍珠",
      "image_url": "https://zhuluoji.cn-sh2.ufileos.com/beads/%E7%8F%8D%E7%8F%A0.png",
      "color": "浅灰色",
      "wuxing": "木、土、火、水、金",
      "english": "Pearl"
    },
    {
      "id": "95",
      "name": "珍珠 1",
      "image_url": "https://zhuluoji.cn-sh2.ufileos.com/beads/%E7%8F%8D%E7%8F%A01.png",
      "color": "绿色",
      "wuxing": "木",
      "english": "Pearl 1"
    },
    {
      "id": "96",
      "name": "珍珠 2",
      "image_url": "https://zhuluoji.cn-sh2.ufileos.com/beads/%E7%8F%8D%E7%8F%A02.png",
      "color": "白色",
      "wuxing": "水",
      "english": "Pearl 2"
    },
    {
      "id": "97",
      "name": "珍珠 3",
      "image_url": "https://zhuluoji.cn-sh2.ufileos.com/beads/%E7%8F%8D%E7%8F%A03.png",
      "color": "白色、粉色",
      "wuxing": "水、金、土、木",
      "english": "Pearl 3"
    },
    {
      "id": "98",
      "name": "珍珠 4",
      "image_url": "https://zhuluoji.cn-sh2.ufileos.com/beads/%E7%8F%8D%E7%8F%A04.png",
      "color": "白色",
      "wuxing": "金、木、水、土",
      "english": "Pearl 4"
    },
    {
      "id": "99",
      "name": "紫翡翠",
      "image_url": "https://zhuluoji.cn-sh2.ufileos.com/beads/%E7%B4%AB%E7%BF%A1%E7%BF%A0.png",
      "color": "紫色",
      "wuxing": "土",
      "english": "Purple Jadeite"
    },
    {
      "id": "100",
      "name": "紫锂云母",
      "image_url": "https://zhuluoji.cn-sh2.ufileos.com/beads/%E7%B4%AB%E9%94%82%E4%BA%91%E6%AF%8D.png",
      "color": "红色",
      "wuxing": "火、土、水、金",
      "english": "Lepidolite"
    },
    {
      "id": "101",
      "name": "紫水晶",
      "image_url": "https://zhuluoji.cn-sh2.ufileos.com/beads/%E7%B4%AB%E6%B0%B4%E6%99%B6.png",
      "color": "紫色",
      "wuxing": "火",
      "english": "Amethyst"
    },
    {
      "id": "102",
      "name": "紫水晶 1",
      "image_url": "https://zhuluoji.cn-sh2.ufileos.com/beads/%E7%B4%AB%E6%B0%B4%E6%99%B61.png",
      "color": "紫色",
      "wuxing": "火、木",
      "english": "Amethyst 1"
    },
    {
      "id": "103",
      "name": "紫水晶 2",
      "image_url": "https://zhuluoji.cn-sh2.ufileos.com/beads/%E7%B4%AB%E6%B0%B4%E6%99%B62.png",
      "color": "紫色",
      "wuxing": "火",
      "english": "Amethyst 2"
    },
    {
      "id": "104",
      "name": "紫水晶 3",
      "image_url": "https://zhuluoji.cn-sh2.ufileos.com/beads/%E7%B4%AB%E6%B0%B4%E6%99%B63.png",
      "color": "紫色",
      "wuxing": "火",
      "english": "Amethyst 3"
    },
    {
      "id": "105",
      "name": "紫水晶 4",
      "image_url": "https://zhuluoji.cn-sh2.ufileos.com/beads/%E7%B4%AB%E6%B0%B4%E6%99%B64.png",
      "color": "紫色",
      "wuxing": "火",
      "english": "Amethyst 4"
    },
    {
      "id": "106",
      "name": "紫幽灵",
      "image_url": "https://zhuluoji.cn-sh2.ufileos.com/beads/%E7%B4%AB%E5%B9%BD%E7%81%B5.png",
      "color": "紫色、橙色、黑色",
      "wuxing": "木",
      "english": "Purple Phantom Quartz"
    },
    {
      "id": "107",
      "name": "紫玉髓",
      "image_url": "https://zhuluoji.cn-sh2.ufileos.com/beads/%E7%B4%AB%E7%8E%89%E9%AB%93.png",
      "color": "紫色",
      "wuxing": "火",
      "english": "Purple Chalcedony"
    }
  ],
  "wuxingIndex": {
    "金": ["1", "2", "3", "5", "6", "7", "8", "9", "11", "13", "14", "20", "21", "33", "37", "42", "46", "47", "48", "74", "77", "85", "91", "94"],
    "木": ["6", "7", "9", "12", "33", "37", "42", "52", "59", "60", "61", "62", "63", "64", "65", "66", "67", "68", "69", "74", "80", "81", "82", "85", "89", "90", "91", "92", "94", "95", "97", "98", "102", "106"],
    "水": ["7", "9", "13", "14", "17", "19", "20", "23", "31", "32", "33", "37", "42", "50", "51", "52", "53", "54", "55", "56", "57", "58", "64", "65", "76", "77", "78", "81", "82", "85", "86", "88", "92", "93", "94", "96", "97", "98", "100"],
    "火": ["4", "5", "7", "9", "11", "12", "14", "15", "16", "17", "18", "24", "25", "26", "27", "28", "29", "30", "33", "37", "42", "43", "44", "70", "71", "72", "75", "79", "83", "84", "87", "91", "92", "94", "99", "100", "101", "102", "103", "104", "105", "107"],
    "土": ["5", "6", "7", "9", "10", "11", "14", "17", "18", "22", "32", "33", "34", "35", "36", "37", "38", "39", "40", "41", "42", "45", "47", "49", "64", "65", "73", "74", "77", "83", "85", "91", "92", "93", "94", "97", "98", "99", "100"]
  }
}